vmshepherd_zookeeper_driver
