Metadata-Version: 1.1
Name: vmshepherd-zookeeper-driver
Version: 0.0.2
Summary: Runtime and lock management for VmShepherd
Home-page: https://github.com/kwarunek/vmshepherd-zookeeper-driver
Author: Krzysztof Warunek
Author-email: krzysztof@warunek.net
License: UNKNOWN
Keywords: vmshepherd,openstack,zookeeper,runtime,lock
Platform: UNKNOWN
Classifier: Programming Language :: Python :: 3.6
Classifier: Programming Language :: Python :: 3.7
Classifier: Operating System :: POSIX
Classifier: Development Status :: 4 - Beta
